materials_commons/script/__init__.py
materials_commons/script/script.py
materials_commons_script-0.1.0.dist-info/LICENSE
materials_commons_script-0.1.0.dist-info/METADATA
materials_commons_script-0.1.0.dist-info/WHEEL
materials_commons_script-0.1.0.dist-info/top_level.txt
materials_commons_script-0.1.0.dist-info/RECORD
