Metadata-Version: 2.1
Name: materials-commons-script
Version: 0.1.0
Summary: Utilities for scripts running on Materials Commons
Home-page: https://materials-commons.github.io/materials-commons-api/html/index.html
Author: Materials Commons development team
Author-email: materials-commons-authors@umich.edu
License: MIT
Keywords: materials science mc materials-commons prisms
Classifier: Development Status :: 4 - Beta
Classifier: Intended Audience :: Developers
Classifier: Intended Audience :: Science/Research
Classifier: Topic :: Scientific/Engineering :: Information Analysis
Classifier: License :: OSI Approved :: MIT License
Classifier: Programming Language :: Python :: 3
Classifier: Programming Language :: Python :: 3.8
License-File: LICENSE
Requires-Dist: requests
Requires-Dist: urllib3
Requires-Dist: materials-commons-api
